{"sections":{"cards-grid":{"type":"cards-grid","blocks":{"block_1":{"type":"column","settings":{"column_start":1,"column_end":3,"row_start":"1","row_end":"3","min_height":"small","padding":"small","image":"shopify:\/\/shop_images\/Mats4U_Home_Page_Logo_Mat_Cover.png","image_size":"cover","icon_size":"cover","icon_position":"left-top","icon_background":"background-2","background_color":"#ffffff","background_effect":"left-gradient","effect_opacity":0.3,"enable_mobile_overlay":true,"text_align":"left","text_color_scheme":"light","subheading":"2024 DEALS","color_text":"#ffffff","show_subheading_dot":true,"color_dot":"#e77817","heading":"LOGO MATS","heading_size":"h3","heading_width":50,"text":"Design Your Own Entrance Mat","text_size":"small","text_width":100,"show_button":true,"button_label":"FREE QUOTE & DESIGN","button_link":"shopify:\/\/pages\/logo-mat-selection","style_button":"button button--primary button--arrow","add_button_label":"","add_button_price":"","card_link":""}},"block_2":{"type":"column","settings":{"column_start":3,"column_end":4,"row_start":"1","row_end":"3","min_height":"small","padding":"small","image":"shopify:\/\/shop_images\/Rubber_Mat.png","image_size":"cover","icon_size":"cover","icon_position":"left-top","icon_background":"background-2","background_color":"#ffffff","background_effect":"none","effect_opacity":0.4,"enable_mobile_overlay":false,"text_align":"left","text_color_scheme":"light","subheading":"In Stock","color_text":"#ffffff","show_subheading_dot":true,"color_dot":"#40b66f","heading":"KITCHEN MATS","heading_size":"h3","heading_width":50,"text":"Rubber mats","text_size":"small","text_width":100,"show_button":true,"button_label":"BUY NOW","button_link":"shopify:\/\/collections\/kitchen-mats","style_button":"button button--primary button--arrow","add_button_label":"","add_button_price":"","card_link":""}},"block_3":{"type":"column","settings":{"column_start":4,"column_end":5,"row_start":"auto","row_end":"auto","min_height":"small","padding":"small","image":"shopify:\/\/shop_images\/wet-area-home-banner.png","image_size":"cover","icon_size":"cover","icon_position":"left-top","icon_background":"background-2","background_color":"#ffffff","background_effect":"none","effect_opacity":0.4,"enable_mobile_overlay":false,"text_align":"left","text_color_scheme":"light","subheading":"IN STOCK","color_text":"#ffffff","show_subheading_dot":true,"color_dot":"#40b66f","heading":"WET AREA","heading_size":"h3","heading_width":50,"text":"MATTING","text_size":"small","text_width":100,"show_button":true,"button_label":"Explore","button_link":"shopify:\/\/collections\/wet-area","style_button":"button button--primary button--arrow","add_button_label":"","add_button_price":"","card_link":""}},"block_4":{"type":"column","settings":{"column_start":4,"column_end":5,"row_start":"auto","row_end":"auto","min_height":"small","padding":"small","image":"shopify:\/\/shop_images\/coir_mats-close-up.png","image_size":"cover","icon_size":"cover","icon_position":"left-top","icon_background":"background-2","background_color":"#ffffff","background_effect":"none","effect_opacity":0.4,"enable_mobile_overlay":false,"text_align":"left","text_color_scheme":"light","subheading":"CUT TO SIZE","color_text":"#ffffff","show_subheading_dot":true,"color_dot":"#40b66f","heading":"COIR","heading_size":"h3","heading_width":50,"text":"SEVERAL COLOURS AVAILABLE","text_size":"small","text_width":100,"show_button":true,"button_label":"SHOP NOW","button_link":"shopify:\/\/collections\/coir-mats","style_button":"button button--primary button--arrow","add_button_label":"","add_button_price":"","card_link":""}}},"block_order":["block_1","block_2","block_3","block_4"],"settings":{"color_scheme":"background-1","columns":4,"margin_top":"no-indent","margin_bottom":"no-indent","padding_top":"no-indent","padding_bottom":"xs"}},"multicolumn":{"type":"multicolumn","blocks":{"column-1":{"type":"column","settings":{"image":"shopify:\/\/shop_images\/Free_Delivery.png","image_2":"shopify:\/\/shop_images\/Free_Delivery.png","heading":"Free Delivery","text":"Orders over £70"}},"column-2":{"type":"column","settings":{"image":"shopify:\/\/shop_images\/100_Guarantee.png","image_2":"shopify:\/\/shop_images\/100_Guarantee.png","heading":"100% Product","text":"Guarantee"}},"column-3":{"type":"column","settings":{"image":"shopify:\/\/shop_images\/30_years_experience.png","image_2":"shopify:\/\/shop_images\/30_years_experience.png","heading":"50 Years","text":"Trading History"}},"column-4":{"type":"column","settings":{"image":"shopify:\/\/shop_images\/secure_payment.png","image_2":"shopify:\/\/shop_images\/secure_payment.png","heading":"Secure","text":"Payments"}}},"block_order":["column-1","column-2","column-3","column-4"],"settings":{"color_scheme":"background-1","multicolumn_to_show":4,"image_type":"image","icon_background":"background-2","image_width":"medium","object_fit":"contain","swipe_on_mobile":true,"border_top":false,"margin_top":"no-indent","margin_bottom":"xs","padding_top":"no-indent","padding_bottom":"no-indent"}},"custom_liquid_6wH3GW":{"type":"custom-liquid","disabled":true,"settings":{"custom_liquid":"<div class=\"essential-banners-block\" id=\"540d67f7-4670-4006-8d31-97af61f1aac5\"><\/div>"}},"featured-products":{"type":"featured-products","settings":{"color_scheme":"background-1","subheading":"","heading":"","heading_size":"h2","show_info":true,"info_subheading":"NEW","info_heading":"WATERHOG","info_heading_size":"h2","text":"Introducing Waterhog, the ultimate entrance mat solution! Designed to trap water and dirt effectively, it keeps your premises clean and dry. Its durable construction ensures longevity, making it a cost-effective choice.","show_button":true,"button_style":"primary","button_label":"Explore More Waterhog","button_link":"shopify:\/\/collections\/waterhog","product_list":["waterhog-diamond-eco-entrance-mat","waterhog-eco-elite-heavy-duty-entrance-matting","waterhog-eco-premier-matting-tiles-geometric","waterhog-modular-forklift-mats-double-sided-tape-installation-system"],"columns_mobile":"1","image_ratio":"square","image_fit":"cover","show_secondary_image":false,"show_vendor":true,"show_desc":false,"show_sku":false,"margin_top":"no-indent","margin_bottom":"no-indent","padding_top":"xs","padding_bottom":"xs"}},"brands":{"type":"brands","blocks":{"column_Jnc8Bk":{"type":"column","settings":{"image_1":"shopify:\/\/shop_images\/Mats4U_client_Logo_1.png","image_2":"shopify:\/\/shop_images\/Mats4U_client_Logo_1.png","image_width":125,"brand_link":""}},"block_1":{"type":"column","settings":{"image_1":"shopify:\/\/shop_images\/Mats4U_client_Logo_2.png","image_2":"shopify:\/\/shop_images\/Mats4U_client_Logo_2.png","image_width":125,"brand_link":""}},"block_2":{"type":"column","settings":{"image_1":"shopify:\/\/shop_images\/Mats4U_client_Logo_3.png","image_2":"shopify:\/\/shop_images\/Mats4U_client_Logo_3.png","image_width":125,"brand_link":""}},"block_3":{"type":"column","settings":{"image_1":"shopify:\/\/shop_images\/Mats4U_client_Logo_5.png","image_2":"shopify:\/\/shop_images\/Mats4U_client_Logo_5.png","image_width":125,"brand_link":""}},"column_kNFprN":{"type":"column","settings":{"image_1":"shopify:\/\/shop_images\/Mats4U_client_Logo_6.png","image_2":"shopify:\/\/shop_images\/Mats4U_client_Logo_6.png","image_width":125,"brand_link":""}},"block_4":{"type":"column","settings":{"image_1":"shopify:\/\/shop_images\/Mats4U_client_Logo_7.png","image_2":"shopify:\/\/shop_images\/Mats4U_client_Logo_7.png","image_width":125,"brand_link":""}},"block_5":{"type":"column","settings":{"image_1":"shopify:\/\/shop_images\/Mats4U_client_Logo_8.png","image_2":"shopify:\/\/shop_images\/Mats4U_client_Logo_8.png","image_width":125,"brand_link":""}},"block_6":{"type":"column","settings":{"image_1":"shopify:\/\/shop_images\/Jaguar_Land_Rover_2022_svg.png","image_2":"shopify:\/\/shop_images\/Jaguar_Land_Rover_2022_svg.png","image_width":125,"brand_link":""}},"block_7":{"type":"column","disabled":true,"settings":{"image_width":60,"brand_link":""}},"block_8":{"type":"column","disabled":true,"settings":{"image_width":60,"brand_link":""}}},"block_order":["column_Jnc8Bk","block_1","block_2","block_3","column_kNFprN","block_4","block_5","block_6","block_7","block_8"],"settings":{"color_scheme":"background-1","border_top":false,"border_bottom":true,"padding_top":"xs","padding_bottom":"no-indent"}},"f985f678-f3e0-4940-a56f-227b4d758eb8":{"type":"countdown","disabled":true,"settings":{"section_type":"simple","date_picker":"2024-03-01","time_picker":"00:00","cursive_date":false,"countdown_block_font":50,"completed_countdown":"show_text","countdown_heading":"<p>Header after countdown<\/p>","opacity_overlay":0.6,"heading":"Some header","text":"Some description.","show_link":true,"button_label":"Shop now","button_style":"primary","button_link":"","margin_top":"no-indent","margin_bottom":"no-indent","padding_top":"m","padding_bottom":"no-indent"}},"product-promo":{"type":"product-promo","blocks":{"block_1":{"type":"column","settings":{"image":"shopify:\/\/shop_images\/tall-vibrant-green-grass-cover-rolling-hillside.jpg","image_size":"cover","opacity_overlay":0.4,"background_color":"#cccccc","product":"supercoir-heavy-duty-coir-coconut-roll-matting","text_color_scheme":"light","subheading":"100% Natural","color_text":"#ffffff","show_subheading_dot":false,"color_dot":"#40b66f","heading":"Explore Our Coir Mats","heading_size":"h2","text":"Our 100% natural eco-friendly coir mats are crafted from high-quality coconut fibres, offering a sustainable and biodegradable solution for your home. These mats are not only durable and resilient, ensuring long-lasting use, but also feature a natural aesthetic that complements any décor. The coarse texture effectively traps dirt and debris, keeping your floors clean while minimizing your environmental footprint. Perfect for both indoor and outdoor use, our coir mats provide a stylish and environmentally conscious choice for maintaining a tidy and welcoming entryway.","show_button":true,"button_style":"primary","button_label":"Explore","button_link":"shopify:\/\/collections\/coir-mats"}},"block_2":{"type":"column","settings":{"image":"shopify:\/\/shop_images\/Anti_slip_mat_whet_aria.png","image_size":"cover","opacity_overlay":0.5,"background_color":"#cccccc","product":"heronrib-wet-area-non-slip-mats","text_color_scheme":"light","subheading":"Subheading","color_text":"#ffffff","show_subheading_dot":true,"color_dot":"#40b66f","heading":"Non Slip Matting","heading_size":"h2","text":"Our non-slip matting offers a lightweight, economical solution for wet areas. It's non-porous, oil and chemical resistant, with an etched surface for traction. Featuring anti-microbial and anti-fungal properties, it's ideal for continuous hygiene in humid environments. UV resistant for indoor\/outdoor use, it comes in rolls or tiles for easy installation. Perfect for various settings, our matting ensures safety and comfort, preventing accidents and enhancing any space with its practicality and durability.\nMats4U has a large range for you to explore","show_button":true,"button_style":"primary","button_label":"Explore","button_link":"shopify:\/\/collections\/wet-area"}}},"block_order":["block_1","block_2"],"settings":{"color_scheme":"background-1","columns_per_row":"2","margin_top":"no-indent","margin_bottom":"no-indent","padding_top":"m","padding_bottom":"no-indent","image_ratio":"square","image_fit":"cover","show_secondary_image":false,"show_vendor":true,"show_sku":false}},"featured_blog_1":{"type":"featured-blog","settings":{"color_scheme":"background-1","color_scheme_card":"background-2","subheading":"","heading":"Guides for Everything You Need","heading_size":"h3","post_layout":"column-icon","image_width":"medium","image_fit":"contain","icon_background":"background-1","blog":"guides","post_limit":6,"post_limit_mobile":3,"show_image":false,"show_tags":false,"show_date":false,"show_author":false,"show_excerpt":true,"show_view_all":true,"show_view_all_mobile":true,"button_label":"View All Guides","button_style":"primary","padding_top":"xs","padding_bottom":"no-indent"}},"popular-products":{"type":"popular-products","settings":{"heading":"Top Rated Products","collection_list":["chair-mats","gym-mats","anti-fatigue-mats","outdoor","well-recess","kitchen-mats","entrance-mats"],"products_limit":6,"products_to_show":4,"filter":true,"filter_type":"collections","show_vendor":true,"show_sku":false,"image_ratio":"square","image_fit":"cover","padding_top":"xs","padding_bottom":"xs"}},"featured-product":{"type":"featured-product","blocks":{"block_1":{"type":"text","settings":{"text":"Supplied","vendor_url":""}},"block_2":{"type":"rating","settings":{}},"block_3":{"type":"title","settings":{"heading_size":"h2"}},"block_4":{"type":"price","settings":{}},"block_5":{"type":"variant_picker","settings":{"picker_type":"button"}},"block_6":{"type":"buy_buttons","settings":{"show_dynamic_checkout":true,"show_quantity":true}}},"block_order":["block_1","block_2","block_3","block_4","block_5","block_6"],"settings":{"product_item":"ecotex-rectangular-chair-mat","color_scheme":"background-2","heading":"This Weeks Best Seller","padding_top":"no-indent","padding_bottom":"xs"}},"custom_liquid_VzaacU":{"type":"custom-liquid","settings":{"custom_liquid":"<!-- TrustBox widget - Carousel -->\n<div class=\"trustpilot-widget\" data-locale=\"en-US\" data-template-id=\"53aa8912dec7e10d38f59f36\" data-businessunit-id=\"4f352767000064000512cae7\" data-style-height=\"140px\" data-style-width=\"100%\" data-theme=\"light\" data-stars=\"4,5\" data-review-languages=\"en\">\n  <a href=\"https:\/\/www.trustpilot.com\/review\/mats4u.co.uk\" target=\"_blank\" rel=\"noopener\">Trustpilot<\/a>\n<\/div>\n<!-- End TrustBox widget -->"}},"81962f3e-586c-417a-9567-dbeea81ebf11":{"type":"slideshow","blocks":{"template--18876850438419__81962f3e-586c-417a-9567-dbeea81ebf11-16831840189de12f5f-0":{"type":"slide","settings":{"color_scheme":"background-3","subheading":"Highest Quality","heading":"Logo Mats","heading_size":"medium","description":"We provide only the best!","show_button":true,"button_style":"primary","button_label":"Explore Our Store","button_link":"","image":"shopify:\/\/shop_images\/Berber_Logo_Mat_Mats4U.png","overlay_opacity":0.5}},"template--18876850438419__81962f3e-586c-417a-9567-dbeea81ebf11-16831840189de12f5f-1":{"type":"slide","settings":{"color_scheme":"background-3","subheading":"Super Safe","heading":"Wet Area Matting","heading_size":"medium","description":"Your safety is important to us","show_button":true,"button_style":"primary","button_label":"Explore Our Store","button_link":"","image":"shopify:\/\/shop_images\/Heronrib-Pool-Wet-Area-Matting_7e464a61-294f-4b3a-a066-795077055339.jpg","overlay_opacity":0.5}}},"block_order":["template--18876850438419__81962f3e-586c-417a-9567-dbeea81ebf11-16831840189de12f5f-0","template--18876850438419__81962f3e-586c-417a-9567-dbeea81ebf11-16831840189de12f5f-1"],"disabled":true,"settings":{"color_scheme":"background-1","full_width":true,"height":"21\/9","enable_autoplay":true,"slide_duration":5,"controls_color_scheme":"light","padding_top":"xs","padding_bottom":"no-indent","margin_top":"no-indent","margin_bottom":"no-indent"}},"categories-list":{"type":"categories-list","blocks":{"collection_1":{"type":"collection_item","settings":{"collection":"coir-mats"}},"collection_2":{"type":"collection_item","settings":{"collection":"anti-fatigue-mats"}},"collection_3":{"type":"collection_item","settings":{"collection":"entrance-mats"}},"collection_4":{"type":"collection_item","settings":{"collection":"chair-mats"}},"collection_5":{"type":"collection_item","settings":{"collection":"forklift-truck-mats"}},"collection_6":{"type":"collection_item","disabled":true,"settings":{"collection":"outdoor"}}},"block_order":["collection_1","collection_2","collection_3","collection_4","collection_5","collection_6"],"settings":{"color_scheme":"background-1","heading":"Explore Our most viewed Collections","image_ratio":"square","image_fit":"cover","collections_to_show":6,"padding_top":"s","padding_bottom":"xs"}},"8c56d2e5-9685-4f40-a0e6-22a8d1b85096":{"type":"compare","disabled":true,"settings":{"heading":"Subheading","title":"Some header","text":"Some description","show_button":false,"button_style":"primary","button_label":"Explore Our Store","button_link":"","margin_top":"no-indent","margin_bottom":"no-indent","padding_top":"m","padding_bottom":"no-indent"}},"product_promo_rqXLGb":{"type":"product-promo","blocks":{"column_mUfDNq":{"type":"column","settings":{"image":"shopify:\/\/shop_images\/Office_environment.png","image_size":"cover","opacity_overlay":0.4,"background_color":"#cccccc","product":"anti-microbial-rectangular-chair-mat","text_color_scheme":"light","subheading":"Enhance Your Workspace with Our Premium Office Chair Mats!","color_text":"#ffffff","show_subheading_dot":false,"color_dot":"#40b66f","heading":"Office Mats","heading_size":"h2","text":"Upgrade your office setup with our high-quality office chair mats, designed to protect your floors and provide smooth, effortless movement for your chair. Crafted from durable materials, our mats are perfect for any workspace, ensuring both comfort and style. Say goodbye to scratches and wear – order your office chair mat today and experience the difference!","show_button":true,"button_style":"primary","button_label":"Explore Our Store","button_link":"shopify:\/\/collections\/chair-mats"}},"column_KkVtXL":{"type":"column","settings":{"image":"shopify:\/\/shop_images\/Factory_space.png","image_size":"cover","opacity_overlay":0.4,"background_color":"#cccccc","product":"deckplate-anti-fatigue-mat","text_color_scheme":"light","subheading":"Boost Efficiency and Safety with Our High-Quality Factory Environment Mats!","color_text":"#ffffff","show_subheading_dot":false,"color_dot":"#40b66f","heading":"Revolutionize Your Factory Floor with Our Top-Grade Mats!","heading_size":"h2","text":"Enhance your factory’s productivity and safety with our robust factory environment mats. Engineered to withstand heavy use, our mats provide superior anti-fatigue properties, slip resistance, and protection for your floors. Ideal for assembly lines, workstations, and high-traffic areas, our durable mats help create a safer and more comfortable working environment. Upgrade your factory floor today for improved efficiency and worker well-being!","show_button":false,"button_style":"primary","button_label":"Explore Our Store","button_link":""}}},"block_order":["column_mUfDNq","column_KkVtXL"],"settings":{"color_scheme":"background-1","columns_per_row":"2","margin_top":"no-indent","margin_bottom":"no-indent","padding_top":"s","padding_bottom":"no-indent","image_ratio":"square","image_fit":"cover","show_secondary_image":true,"show_vendor":true,"show_sku":false}},"a569544e-3aba-492f-a6a1-aa3988de4cef":{"type":"collapsible-content","blocks":{"template--18876850438419__a569544e-3aba-492f-a6a1-aa3988de4cef-16831841146a7cb38f-0":{"type":"accordion","settings":{"question":"What Are Mats4U Anti-Fatigue Mats?","answer":"<p><a href=\"\/collections\/anti-fatigue-mats\" target=\"_blank\" title=\"Anti Fatigue Mats\"><strong>Anti-Fatigue Mats<\/strong><\/a><strong> <\/strong>are ergonomically designed to provide superior cushioning and minimize the strain on feet, legs, back, and neck during long standing periods. They are an essential part of a healthy workplace environment. <a href=\"\/blogs\/guides\" title=\"Guides\"><strong>READ MORE HERE<\/strong><\/a><\/p><p><\/p><p>The antimicrobial properties of these mats are integrated into the mat itself, ensuring long-lasting effectiveness. This feature makes them a perfect choice for areas where hygiene is crucial, such as food preparation areas, hospitals, clinics, daycare centres, kitchens, behind bars, workstations, heavy Industrial Anti Fatigue, machine shops, walk-in freezers, wet areas, external entrances.<\/p>","opened":false}},"template--18876850438419__a569544e-3aba-492f-a6a1-aa3988de4cef-16831841146a7cb38f-1":{"type":"accordion","settings":{"question":"Why is there extended Lead times on some of your Matting Products?","answer":"<p>At Mats4U, we prioritize the quality and longevity of our products. While we strive to deliver our stock items promptly, many of our mats are manufactured upon order, even if they are of standard size. This approach is driven by our commitment to quality control.<\/p><p>Rubber, a key component in our mats, has a shelf life of approximately four to five years. To ensure that we provide you with the best possible products, we manufacture the rubber for your mat in the same week it is delivered. This practice guarantees that you receive a brand new product that hasn’t been sitting on a shelf for months.<\/p><p>By choosing to manufacture on order, we can ensure that every mat you purchase from us is fresh, high-quality, and made to last. We believe that this commitment to quality is worth the slightly extended lead time and we hope that our customers agree. Thank you for your understanding and patience.<\/p>","opened":false}},"template--18876850438419__a569544e-3aba-492f-a6a1-aa3988de4cef-16831841146a7cb38f-2":{"type":"accordion","settings":{"question":"Where do you source your Mats?","answer":"<p>At Mats4U, we take pride in the quality and origin of our products. The <strong>majority of our mats are manufactured in the United Kingdom<\/strong> and dispatched directly from our warehouse located in Sutton Coldfield. This allows us to ensure high-quality standards and swift delivery times for our UK customers.<\/p><p>In instances where a requested product is not available within the UK, we have established reliable supply chains across the European Union and the United States. This enables us to source and deliver a wide variety of mats to meet the diverse needs of our customers. Regardless of the origin, every mat we sell adheres to our stringent quality standards, ensuring you receive a product that is durable, functional, and aesthetically pleasing. Thank you for choosing Mats4U, your trusted matting solution provider.<\/p>","opened":false}}},"block_order":["template--18876850438419__a569544e-3aba-492f-a6a1-aa3988de4cef-16831841146a7cb38f-0","template--18876850438419__a569544e-3aba-492f-a6a1-aa3988de4cef-16831841146a7cb38f-1","template--18876850438419__a569544e-3aba-492f-a6a1-aa3988de4cef-16831841146a7cb38f-2"],"settings":{"heading":"Frequently Asked Questions","heading_size":"h3","text":"","margin_top":"no-indent","margin_bottom":"no-indent","padding_top":"xs","padding_bottom":"l"}},"featured_blog_2":{"type":"featured-blog","settings":{"color_scheme":"background-1","color_scheme_card":"background-2","subheading":"Mats4U Trusted Matting Solutions","heading":"Latest Blogs","heading_size":"h3","post_layout":"column","image_width":"small","image_fit":"contain","icon_background":"background-2","blog":"news","post_limit":6,"post_limit_mobile":2,"show_image":true,"show_tags":false,"show_date":false,"show_author":false,"show_excerpt":false,"show_view_all":true,"show_view_all_mobile":true,"button_label":"Explore all","button_style":"secondary","padding_top":"no-indent","padding_bottom":"no-indent"}},"image_banner_t6hDaD":{"type":"image-banner","disabled":true,"settings":{"full_width":false,"color_scheme":"background-1","subheading":"","heading":"<p>Some header for your collection<\/p>","heading_size":"medium","text_information":"Some descriptive text for your collection. For better alignment, it is better to use text in several lines.","text_align":"left","show_view_all":false,"button_label":"Shop now","button_style":"primary","button_link":"","image_ratio":"adapt","opacity_overlay":0.5,"margin_top":"no-indent","margin_bottom":"no-indent"}},"custom_liquid_kPEfky":{"type":"custom-liquid","custom_css":[],"settings":{"custom_liquid":"<!-- TrustBox widget - Horizontal -->\n<div id=\"trustpilot-widget\" class=\"trustpilot-widget\" data-locale=\"en-US\" data-template-id=\"5406e65db0d04a09e042d5fc\" data-businessunit-id=\"4f352767000064000512cae7\" data-style-height=\"28px\" data-style-width=\"100%\" data-theme=\"light\">\n  <a href=\"https:\/\/www.trustpilot.com\/review\/mats4u.co.uk\" target=\"_blank\" rel=\"noopener\">Trustpilot<\/a>\n<\/div>\n<!-- End TrustBox widget -->"}}},"order":["cards-grid","multicolumn","custom_liquid_6wH3GW","featured-products","brands","f985f678-f3e0-4940-a56f-227b4d758eb8","product-promo","featured_blog_1","popular-products","featured-product","custom_liquid_VzaacU","81962f3e-586c-417a-9567-dbeea81ebf11","categories-list","8c56d2e5-9685-4f40-a0e6-22a8d1b85096","product_promo_rqXLGb","a569544e-3aba-492f-a6a1-aa3988de4cef","featured_blog_2","image_banner_t6hDaD","custom_liquid_kPEfky"]}